yxdb/__init__.py
yxdb/_buffered_record_reader.py
yxdb/_extractors.py
yxdb/_lzf.py
yxdb/_metainfo_field.py
yxdb/_utility.py
yxdb/_yxdb_record.py
yxdb/spatial.py
yxdb/yxdb_field.py
yxdb/yxdb_reader.py
yxdb-1.1.1.dist-info/LICENSE
yxdb-1.1.1.dist-info/METADATA
yxdb-1.1.1.dist-info/WHEEL
yxdb-1.1.1.dist-info/top_level.txt
yxdb-1.1.1.dist-info/RECORD
