Metadata-Version: 2.1
Name: yxdb
Version: 1.1.1
Summary: Reads Alteryx data files into Python
Author-email: tlarsendataguy <tom@tlarsendataguy.com>
License: MIT License
Project-URL: Homepage, https://github.com/tlarsendataguy-yxdb/yxdb-py
Project-URL: Bug Tracker, https://github.com/tlarsendataguy-yxdb/yxdb-py/issues
Classifier: Programming Language :: Python :: 3
Classifier: License :: OSI Approved :: MIT License
Classifier: Operating System :: OS Independent
Requires-Python: >=3.6
License-File: LICENSE
